[{"language": "C#", "percentage": 35.444300371068366, "color": {"color": "#178600", "url": "https://github.com/trending?l=Csharp"}}, {"language": "Python", "percentage": 29.691492521034903, "color": {"color": "#3572A5", "url": "https://github.com/trending?l=Python"}}, {"language": "TypeScript", "percentage": 8.556896426688606, "color": {"color": "#3178c6", "url": "https://github.com/trending?l=TypeScript"}}, {"language": "JavaScript", "percentage": 8.511044730481734, "color": {"color": "#f1e05a", "url": "https://github.com/trending?l=JavaScript"}}, {"language": "HTML", "percentage": 7.648141979950513, "color": {"color": "#e34c26", "url": "https://github.com/trending?l=HTML"}}, {"language": "CSS", "percentage": 4.393077317726177, "color": {"color": "#663399", "url": "https://github.com/trending?l=CSS"}}, {"language": "Fluent", "percentage": 2.616514630627205, "color": {"color": "#ffcc33", "url": "https://github.com/trending?l=Fluent"}}, {"language": "Batchfile", "percentage": 1.676080714148083, "color": {"color": "#C1F12E", "url": "https://github.com/trending?l=Batchfile"}}, {"language": "Shell", "percentage": 0.7944732931003611, "color": {"color": "#89e051", "url": "https://github.com/trending?l=Shell"}}, {"language": "SCSS", "percentage": 0.509299020634393, "color": {"color": "#c6538c", "url": "https://github.com/trending?l=SCSS"}}, {"language": "Dockerfile", "percentage": 0.10194275185010895, "color": {"color": "#384d54", "url": "https://github.com/trending?l=Dockerfile"}}, {"language": "PLpgSQL", "percentage": 0.05316949059065894, "color": {"color": "#336790", "url": "https://github.com/trending?l=PLpgSQL"}}, {"language": "Ruby", "percentage": 0.0035667520989053586, "color": {"color": "#701516", "url": "https://github.com/trending?l=Ruby"}}]